sparkenforce/__init__.py
sparkenforce-1.0.0.dist-info/METADATA
sparkenforce-1.0.0.dist-info/WHEEL
sparkenforce-1.0.0.dist-info/licenses/LICENSE
sparkenforce-1.0.0.dist-info/RECORD
