Metadata-Version: 2.4
Name: sparkenforce
Version: 1.0.0
Summary: Type annotation system that allows you to specify and validate the schema of PySpark DataFrames using Python type hints for both function arguments and return values.
Project-URL: homepage, https://github.com/agustin-recoba/sparkenforce
Project-URL: repository, https://github.com/agustin-recoba/sparkenforce.git
Project-URL: documentation, https://github.com/agustin-recoba/sparkenforce
Project-URL: issues, https://github.com/agustin-recoba/sparkenforce/issues
Author-email: Agustín Recoba <agustin.recoba@outlook.com>
License: Apache Software License 2.0
License-File: LICENSE
Keywords: python
Classifier: Development Status :: 4 - Beta
Classifier: Programming Language :: Python
Classifier: Programming Language :: Python :: 3
Classifier: Programming Language :: Python :: 3.10
Classifier: Programming Language :: Python :: 3.11
Classifier: Programming Language :: Python :: 3.12
Classifier: Programming Language :: Python :: 3.13
Classifier: Typing :: Typed
Requires-Python: >=3.7
Requires-Dist: pyspark>=3.0.0
